simple_ruuvitag/__init__.py
simple_ruuvitag/data_formats.py
simple_ruuvitag/decoder.py
simple_ruuvitag/log.py
simple_ruuvitag/ruuvi.py
simple_ruuvitag/adaptors/__init__.py
simple_ruuvitag/adaptors/bleson.py
simple_ruuvitag/adaptors/dummy.py
simple_ruuvitag-0.0.8.dist-info/LICENSE
simple_ruuvitag-0.0.8.dist-info/METADATA
simple_ruuvitag-0.0.8.dist-info/WHEEL
simple_ruuvitag-0.0.8.dist-info/top_level.txt
simple_ruuvitag-0.0.8.dist-info/zip-safe
simple_ruuvitag-0.0.8.dist-info/RECORD
