Metadata-Version: 2.1
Name: simple-ruuvitag
Version: 0.0.8
Summary: Find RuuviTag sensor beacons and get data from selected sensors
Home-page: https://github.com/ruuvi-friends/simple-ruuvitag
Author: Sergio Isidoro
Author-email: smaisidoro@gmail.com
License: MIT
Download-URL: https://github.com/ruuvi-friends/simple-ruuvitag/archive/v0.0.8.tar.gz
Keywords: RuuviTag BLE
Platform: any
Classifier: Development Status :: 4 - Beta
Classifier: Intended Audience :: Developers
Classifier: License :: OSI Approved :: MIT License
Classifier: Operating System :: OS Independent
Classifier: Programming Language :: Python :: 3
Requires-Dist: bleson (==0.1.8)
